{
  "RefrainAfter": 0,
  "ArabicTitle": "أسبسمس أدام عيد الصعود",
  "EnglishTitle": "Adam Aspasmos for Feast of Ascension",
  "CopticTitle": "`A Pi`xrictoc Pennou;",
  "Hymn": [
    {
      "Type": "Base",
      "Rule": 0,
      "Visible": true,
      "Side": "People",
      "Arabic": "الشعب:",
      "Coptic": "Pilaoc>",
      "English": "People:",
      "Arabiccoptic": "بيلاؤس:",
      "Englishcoptic": "Pi-Laos:"
    },
    {
      "Type": "Base",
      "Rule": 0,
      "Visible": true,
      "Side": "North",
      "Arabic": "المسيح إلهنا، قام من بين الأموات، وصعد إلى السموات، وجلس عن يمين أبيه.",
      "Coptic": "`A Pi`xrictoc Pennou;> twnf `ebol =en nheqmwout> ouo\\ af]enaf `e`p]wi `enivhou`i> af\\emci caou`inam `mPefiwt.",
      "English": "Christ our God, has risen from the dead, and ascended into the heavens, He is seated at the right hand of His Father.",
      "Arabiccoptic": " آ بي خريستوس بين نوتي: طونف إيفول خين ني إثموأووت: أووه آفشيناف إيه إبشوي إيه ني في أووي: آفهيمسي صا أووي نام إمبيف يوت . ",
      "Englishcoptic": "-A Pikhristos Pen-nooti-: toonf evol khen- nee-ethmo-oot: owoh afshen-af eepshooi en-iveeoo-ee: afhemsi saoo-een-am emPefioot."
    }
  ]
}