{
  "RefrainAfter": 0,
  "ArabicTitle": "50:6,32:10 مزمور",
  "EnglishTitle": "Psalm 50:6,32:10 ",
  "Hymn": [
    {
      "Type": "Base",
      "Rule": 0,
      "Visible": true,
      "Side": "North",
      "Arabic": "لِكَيمَا تَتَبَرَّرَ فِي اَقْوَالِكَ وَتَغْلِبَ اِذَا حُوكِمْتَ",
      "Coptic": "|opwc `ntekmai =en nekcaji> ouo\\ `nteksro eknasi\\ap.",
      "English": "That You may be justified in Your words, and overcome when You are judged.",
      "Arabiccoptic": "هو بوس إنتيك ماى خين نيك ساجى أووه إنتك اتشرو إك ناتشي هاب",
      "Englishcoptic": "Hopos entek mai khen nek saji. owoh entek etchro eknachi hab."
    },
    {
      "Type": "Base",
      "Rule": 0,
      "Visible": true,
      "Side": "North",
      "Arabic": "الرَّبُّ يُفَرِّقُ مُؤَامَرَةِ الأُمَمِ وَيُرْذِلُ أَفْكَارَ الشُعُوبِ. الليلويا.",
      "Coptic": "Psoic najer nicosni `nte nieqnoc `ebol ouo\\ `fna]o]f `nnimokmek `nte \\anlaoc al?.",
      "English": "The Lord scatters abroad the counsels of the nations, and He sets aside the reasoning of peoples. Alleluia.",
      "Arabiccoptic": "ابشويس ناجير نى سوتشنى إنتى نى إثنوس ايفول. أووه إفنا شوشف إن نى موكميك إنتى هان لاؤس الليلويا",
      "Englishcoptic": "Epshois nageer ni sotchne ente ni ethnos evol. owoh efna shoshf enni mokmek ente han laos. Alleluia"
    }
  ]
}