{
    "Main": [
        {
            "Type": "Main",
            "Path": "PaschaPsalmIntro",
            "Rule": 0,
            "Visible": true
        },
        {
            "Type": "Main",
            "Path": "PaschaThursdayThursdayEveSixthPsalm",
            "Rule": 0,
            "Visible": true
        },
        {
            "Type": "Main",
            "Path": "PaschaGospelIntro",
            "Rule": 3,
            "Visible": true
        },
        {
            "Type": "Main",
            "Path": "PaschaThursdayThursdayEveSixthGospel1",
            "Rule": 0,
            "Visible": true
        },
        {
            "Type": "Main",
            "Path": "PaschaGospelConclusion",
            "Rule": 0,
            "Visible": true
        }
    ]
}