{
    "Main": [
        {
            "Type": "Main",
            "Path": "PaschaPropheciesIntroduction",
            "Rule": "Jeremiah",
            "Visible": true
        },
        {
            "Type": "Main",
            "Path": "PaschaFridayFridayEveNinthProphecies1",
            "Rule": 0,
            "Visible": true
        },
        {
            "Type": "Main",
            "Path": "PaschaPropheciesConclusion",
            "Rule": 0,
            "Visible": true
        },
        {
            "Type": "Main",
            "Path": "PaschaPropheciesIntroduction",
            "Rule": "Ezekiel",
            "Visible": true
        },
        {
            "Type": "Main",
            "Path": "PaschaFridayFridayEveNinthProphecies2",
            "Rule": 0,
            "Visible": true
        },
        {
            "Type": "Main",
            "Path": "PaschaPropheciesConclusion",
            "Rule": 0,
            "Visible": true
        }
    ]
}